[
  {
    "id": 1,
    "name": "極限飛馳籃球鞋",
    "brand_name": "Anta",
    "sport_name": "籃球",
    "price": 880,
    "stock": 50,
    "specs": {
      "商品名稱": "極限飛馳籃球鞋",
      "品牌": "Anta",
      "運動種類": "籃球",
      "材質": "透氣網布與耐磨橡膠",
      "尺寸": "27",
      "重量": 380,
      "產地": "越南"
    },
    "img": "spec01.jpeg"
  },
  {
    "id": 2,
    "name": "標準七號籃球",
    "brand_name": "Spalding",
    "sport_name": "籃球",
    "price": 650,
    "stock": 100,
    "specs": {
      "商品名稱": "標準七號籃球",
      "品牌": "Spalding",
      "運動種類": "籃球",
      "材質": "高級合成皮革",
      "尺寸": "24",
      "重量": 600,
      "產地": "泰國"
    },
    "img": "spec02.jpeg"
  },
  {
    "id": 3,
    "name": "7號籃球",
    "brand_name": "Spalding",
    "sport_name": "籃球",
    "price": 720,
    "stock": 14,
    "specs": {
      "商品名稱": "7號籃球",
      "品牌": "Spalding",
      "運動種類": "籃球",
      "材質": "合成皮",
      "尺寸": "24.5",
      "重量": 600,
      "產地": "中國"
    },
    "img": "spec03.jpeg"
  },
  {
    "id": 4,
    "name": "訓練背心",
    "brand_name": "Nike",
    "sport_name": "籃球",
    "price": 950,
    "stock": 15,
    "specs": {
      "商品名稱": "訓練背心",
      "品牌": "Nike",
      "運動種類": "籃球",
      "材質": "速乾滌綸",
      "尺寸": "1",
      "重量": 181,
      "產地": "越南"
    },
    "img": "spec04.jpeg"
  },
  {
    "id": 5,
    "name": "運動長襪",
    "brand_name": "Nike",
    "sport_name": "籃球",
    "price": 750,
    "stock": 18,
    "specs": {
      "商品名稱": "運動長襪",
      "品牌": "Nike",
      "運動種類": "籃球",
      "材質": "運動棉",
      "尺寸": "25-27",
      "重量": 97,
      "產地": "台灣"
    },
    "img": "spec05.jpeg"
  },
  {
    "id": 6,
    "name": "經典運動短褲",
    "brand_name": "Nike",
    "sport_name": "籃球",
    "price": 890,
    "stock": 20,
    "specs": {
      "商品名稱": "經典運動短褲",
      "品牌": "Nike",
      "運動種類": "籃球",
      "材質": "皮革與氣墊科技",
      "尺寸": "45",
      "重量": 463,
      "產地": "印尼"
    },
    "img": "spec06.jpeg"
  },
  {
    "id": 7,
    "name": "攻擊型碳素羽球拍",
    "brand_name": "Yonex",
    "sport_name": "羽球",
    "price": 820,
    "stock": 30,
    "specs": {
      "商品名稱": "攻擊型碳素羽球拍",
      "品牌": "Yonex",
      "運動種類": "羽球",
      "材質": "高剛性碳纖維",
      "尺寸": "67",
      "重量": 83,
      "產地": "日本"
    },
    "img": "spec07.jpeg"
  },
  {
    "id": 8,
    "name": "比賽級鵝毛羽球",
    "brand_name": "VICTOR",
    "sport_name": "羽球",
    "price": 750,
    "stock": 150,
    "specs": {
      "商品名稱": "比賽級鵝毛羽球",
      "品牌": "VICTOR",
      "運動種類": "羽球",
      "材質": "天然鵝毛",
      "尺寸": "8",
      "重量": 60,
      "產地": "中國"
    },
    "img": "spec08.jpeg"
  },
  {
    "id": 9,
    "name": "碳纖維羽球拍",
    "brand_name": "Yonex",
    "sport_name": "羽球",
    "price": 850,
    "stock": 23,
    "specs": {
      "商品名稱": "碳纖維羽球拍",
      "品牌": "Yonex",
      "運動種類": "羽球",
      "材質": "高彈性碳纖維",
      "尺寸": "83",
      "重量": 84,
      "產地": "日本"
    },
    "img": "spec09.jpeg"
  },
  {
    "id": 10,
    "name": "羽球發射器",
    "brand_name": "VICTOR",
    "sport_name": "羽球",
    "price": 790,
    "stock": 4,
    "specs": {
      "商品名稱": "羽球發射器",
      "品牌": "VICTOR",
      "運動種類": "羽球",
      "材質": "ABS工程塑料",
      "尺寸": "60*40*50",
      "重量": 4510,
      "產地": "中國"
    },
    "img": "spec10.jpeg"
  },
  {
    "id": 11,
    "name": "羽球(一桶12入)",
    "brand_name": "Yonex",
    "sport_name": "羽球",
    "price": 500,
    "stock": 18,
    "specs": {
      "商品名稱": "羽球(一桶12入)",
      "品牌": "Yonex",
      "運動種類": "羽球",
      "材質": "羽毛",
      "尺寸": "7",
      "重量": 6,
      "產地": "越南"
    },
    "img": "spec11.jpeg"
  },
  {
    "id": 12,
    "name": "成人羽球拍",
    "brand_name": "VICTOR",
    "sport_name": "羽球",
    "price": 860,
    "stock": 10,
    "specs": {
      "商品名稱": "成人羽球拍",
      "品牌": "VICTOR",
      "運動種類": "羽球",
      "材質": "碳拍",
      "尺寸": "100",
      "重量": 85,
      "產地": "台灣"
    },
    "img": "spec12.jpeg"
  },
  {
    "id": 13,
    "name": "五星級成品桌球拍",
    "brand_name": "Butterfly",
    "sport_name": "桌球",
    "price": 780,
    "stock": 50,
    "specs": {
      "商品名稱": "五星級成品桌球拍",
      "品牌": "Butterfly",
      "運動種類": "桌球",
      "材質": "純木底板與進口膠皮",
      "尺寸": "15x16",
      "重量": 185,
      "產地": "日本"
    },
    "img": "spec13.jpeg"
  },
  {
    "id": 14,
    "name": "三星訓練桌球",
    "brand_name": "Butterfly",
    "sport_name": "桌球",
    "price": 300,
    "stock": 100,
    "specs": {
      "商品名稱": "三星訓練桌球",
      "品牌": "Butterfly",
      "運動種類": "桌球",
      "材質": "ABS新材料",
      "尺寸": "4",
      "重量": 3,
      "產地": "中國"
    },
    "img": "spec14.jpeg"
  },
  {
    "id": 15,
    "name": "桌球拍組",
    "brand_name": "Butterfly",
    "sport_name": "桌球",
    "price": 700,
    "stock": 90,
    "specs": {
      "商品名稱": "桌球拍組",
      "品牌": "Butterfly",
      "運動種類": "桌球",
      "材質": "五層純木底板與入門級反膠",
      "尺寸": "24*16",
      "重量": 175,
      "產地": "日本"
    },
    "img": "spec15.jpeg"
  },
  {
    "id": 16,
    "name": "快攻桌球拍",
    "brand_name": "Butterfly",
    "sport_name": "桌球",
    "price": 890,
    "stock": 20,
    "specs": {
      "商品名稱": "快攻桌球拍",
      "品牌": "Butterfly",
      "運動種類": "桌球",
      "材質": "檜木夾層",
      "尺寸": "157*150",
      "重量": 86,
      "產地": "瑞典"
    },
    "img": "spec16.jpeg"
  }
]
